jdm_kivy/Jconfig.py
jdm_kivy/Jfunctions.py
jdm_kivy/Jlabel.py
jdm_kivy/Jlogger.py
jdm_kivy/Jscreen.py
jdm_kivy/Jwidget.py
jdm_kivy/Jwindow.py
jdm_kivy/__init__.py
jdm_kivy/config.json
jdm_kivy/assets/font/consolas/consolas_bold.ttf
jdm_kivy/assets/font/consolas/consolas_italic.ttf
jdm_kivy/assets/font/consolas/consolas_italic_bold.ttf
jdm_kivy/assets/font/consolas/consolas_regular.ttf
JDM_kivy-0.0.4.dist-info/LICENSE
JDM_kivy-0.0.4.dist-info/METADATA
JDM_kivy-0.0.4.dist-info/WHEEL
JDM_kivy-0.0.4.dist-info/top_level.txt
JDM_kivy-0.0.4.dist-info/RECORD
