Metadata-Version: 2.1
Name: JDM-kivy
Version: 0.0.4
Summary: JDM-Kivy
Home-page: https://github.com/JDM-Github/JDM-Kivy
Author: JDM
Author-email: jdmaster888@gmail.com
Project-URL: Bug Tracker, https://github.com/JDM-Github/JDM-Kivy/issues
Classifier: Programming Language :: Python :: 3
Classifier: License :: OSI Approved :: MIT License
Classifier: Operating System :: OS Independent
Requires-Python: >=3.6
License-File: LICENSE
